foodutils.py
foodutils-0.1.0.dist-info/top_level.txt
foodutils-0.1.0.dist-info/RECORD
foodutils-0.1.0.dist-info/DESCRIPTION.rst
foodutils-0.1.0.dist-info/METADATA
foodutils-0.1.0.dist-info/metadata.json
foodutils-0.1.0.dist-info/WHEEL
